[{
  "_id": {
    "$oid": "652e958752237ef2e2e812f0"
  },
  "filename": "file-1697551751903.pdf",
  "originalname": "FNLPB7375E-2024.pdf",
  "path": "public\\uploads\\file-1697551751903.pdf",
  "size": 111553,
  "location": "/uploads/file-1697551751903.pdf",
  "__v": 0
},
{
  "_id": {
    "$oid": "652e95d852237ef2e2e812f2"
  },
  "filename": "file-1697551832059.pdf",
  "originalname": "FNLPB7375E_Q1_2024-25.pdf",
  "path": "public\\uploads\\file-1697551832059.pdf",
  "size": 58773,
  "location": "/uploads/file-1697551832059.pdf",
  "__v": 0
},
{
  "_id": {
    "$oid": "652e9695881e4b5c9d9bd6a1"
  },
  "filename": "file-1697552021134.pdf",
  "originalname": "sachin_pancard.pdf",
  "path": "public\\uploads\\file-1697552021134.pdf",
  "size": 242373,
  "location": "/uploads/file-1697552021134.pdf",
  "__v": 0
},
{
  "_id": {
    "$oid": "652e9eb741bcdb09a1373760"
  },
  "filename": "file-1697554103055.pdf",
  "originalname": "FNLPB7375E-2024.pdf",
  "path": "public\\uploads\\file-1697554103055.pdf",
  "size": 111553,
  "location": "/uploads/file-1697554103055.pdf",
  "__v": 0
},
{
  "_id": {
    "$oid": "652e9f2841bcdb09a1373762"
  },
  "filename": "file-1697554216076.pdf",
  "originalname": "FOS002384968031.pdf",
  "path": "public\\uploads\\file-1697554216076.pdf",
  "size": 241910,
  "location": "/uploads/file-1697554216076.pdf",
  "__v": 0
}]